[
{"group":"Hoho","comment":"SINGAHUTAN : 50*39*21 #HOHOTOGEL"},
{"group":"K86T","comment":"K86TOTO ( KUMBANGEMAS ) : 52*33*46"},
{"group":"453P","comment":"ASEPTOGEL KELINCIHOKI 38*83*41"},
{"group":"JOTUNTOTO","comment":"#JOTUNTOTO(PHOENIXYZ)*87*09*81"},
{"group":"NEMO","comment":"NEMO4D (KUDANILA) : 99*53*78"},
{"group":"DIVA4D","comment":"#DIVA4D (AYAMTIRAM) = 07*48*80"},
{"group":"MASTER KUY","comment":"TOGELKUY BADAKEMAS 99*53*78"},
{"group":"ALLPAS","comment":"Tok99toto ( MACANKUMU ) : 50*39*21"},
{"group":"TOYIB","comment":"#TOYIBSLOT ( KERAHITAM ) : 07*11*48"},
{"group":"JNE","comment":"#JNETOTO(GORILLAWIN)*52*33*46"},
{"group":"VESPA","comment":"VESPATOGEL (RUSAKUGAN) 37*98*03"},
{"group":"OPUNG","comment":"bodufa"},
{"group":"TAFSIR","comment":"SIJITOGEL RUSAKUGAN 37*98*03"},
{"group":"KEI","comment":"#keitogel = (CAPUNGIPUNG) = 55*59*64"},
{"group":"PEDRO","comment":"#PEDRO4D (SINGAHUTAN*87*09*81)"},
{"group":"BUKU MIMPI","comment":"IYATOTO GAJAHAPI 55*59*64"},
{"group":"TIKTAK","comment":"Tiktaktogel / NAGAUNGU / 38 , 83 , 41"}
]
